evenvizion/__init__.py
evenvizion/examples/__init__.py
evenvizion/examples/compare_evenvizion_with_original_video.py
evenvizion/examples/evenvizion_component.py
evenvizion/processing/__init__.py
evenvizion/processing/constants.py
evenvizion/processing/fixed_coordinate_system.py
evenvizion/processing/frame_processing.py
evenvizion/processing/matching.py
evenvizion/processing/utils.py
evenvizion/processing/video_processing.py
evenvizion/visualization/__init__.py
evenvizion/visualization/processing_visualization.py
evenvizion/visualization/stabilization.py
evenvizion-0.9.7.dist-info/LICENSE
evenvizion-0.9.7.dist-info/METADATA
evenvizion-0.9.7.dist-info/WHEEL
evenvizion-0.9.7.dist-info/top_level.txt
evenvizion-0.9.7.dist-info/RECORD
