Metadata-Version: 2.1
Name: evenvizion
Version: 0.9.7
Summary: EvenVizion - is a video-based camera localization component
Home-page: https://github.com/AIHunters/EvenVizion
Author: AIHunters
Author-email: oss@aihunters.com
License: UNKNOWN
Platform: UNKNOWN
Classifier: Programming Language :: Python :: 3
Classifier: License :: OSI Approved :: MIT License
Classifier: Operating System :: OS Independent
Requires-Python: >=3.6
Requires-Dist: imutils (>=0.5.3)
Requires-Dist: numpy (>=1.19.2)
Requires-Dist: opencv-contrib-python (==3.4.2.17)
